cloudflare_ip_filter/__init__.py
cloudflare_ip_filter/ip_filter.py
cloudflare_ip_filter/sample_usage.py
cloudflare_ip_filter-0.2.1.dist-info/METADATA
cloudflare_ip_filter-0.2.1.dist-info/WHEEL
cloudflare_ip_filter-0.2.1.dist-info/top_level.txt
cloudflare_ip_filter-0.2.1.dist-info/RECORD
