Metadata-Version: 2.4
Name: cloudflare-ip-filter
Version: 0.2.1
Summary: Flask middleware to restrict access to Cloudflare IP ranges
Author: Mert Cahit Yigit
Classifier: Programming Language :: Python :: 3
Classifier: Operating System :: OS Independent
Requires-Python: >=3.7
Requires-Dist: flask
Requires-Dist: requests
Dynamic: author
Dynamic: classifier
Dynamic: description
Dynamic: description-content-type
Dynamic: requires-dist
Dynamic: requires-python
Dynamic: summary
